MANIFEST.in
README.md
setup.py
mxnet_tools/__init__.py
mxnet_tools/model_tools.cpython-36m-x86_64-linux-gnu.so
mxnet_tools.egg-info/PKG-INFO
mxnet_tools.egg-info/SOURCES.txt
mxnet_tools.egg-info/dependency_links.txt
mxnet_tools.egg-info/requires.txt
mxnet_tools.egg-info/top_level.txt