Metadata-Version: 1.0
Name: mxnet-tools
Version: 0.0.1
Summary: eyesight 模型工具类封装
Home-page: UNKNOWN
Author: gm
Author-email: 1025304567@qq.com
License: MIT Licence
Keywords: pip,eyesight,mxnet_tools,gm
Platform: any
